nti/__init__.py
nti/wref/__init__.py
nti/wref/configure.zcml
nti/wref/interfaces.py
nti/wref/tests/__init__.py
nti/wref/tests/test_adapters.py
nti.wref-1.1.0.post0.dist-info/AUTHORS
nti.wref-1.1.0.post0.dist-info/LICENSE
nti.wref-1.1.0.post0.dist-info/METADATA
nti.wref-1.1.0.post0.dist-info/WHEEL
nti.wref-1.1.0.post0.dist-info/top_level.txt
nti.wref-1.1.0.post0.dist-info/zip-safe
nti.wref-1.1.0.post0.dist-info/RECORD
