Metadata-Version: 2.1
Name: nti.wref
Version: 1.1.0.post0
Summary: NTI Weak References
Home-page: https://github.com/OpenNTI/nti.wref
Author: Jason Madden
Author-email: jason@nextthought.com
License: Apache
Keywords: Weak References
Classifier: Intended Audience :: Developers
Classifier: Natural Language :: English
Classifier: Operating System :: OS Independent
Classifier: License :: OSI Approved :: Apache Software License
Classifier: Programming Language :: Python :: 3
Classifier: Programming Language :: Python :: 3 :: Only
Classifier: Programming Language :: Python :: 3.10
Classifier: Programming Language :: Python :: 3.11
Classifier: Programming Language :: Python :: 3.12
Classifier: Programming Language :: Python :: 3.13
Classifier: Programming Language :: Python :: Implementation :: CPython
Classifier: Programming Language :: Python :: Implementation :: PyPy
Requires-Python: >=3.10
License-File: LICENSE
License-File: AUTHORS
Requires-Dist: persistent
Requires-Dist: zope.component
Requires-Dist: zope.interface
Provides-Extra: docs
Requires-Dist: sphinx; extra == "docs"
Requires-Dist: sphinx-rtd-theme; extra == "docs"
Requires-Dist: repoze.sphinx.autointerface; extra == "docs"
Provides-Extra: test
Requires-Dist: nti.testing; extra == "test"
Requires-Dist: pyhamcrest; extra == "test"
Requires-Dist: zope.testrunner; extra == "test"
Requires-Dist: coverage; extra == "test"
